newmath.py
newmath-0.2.2.dist-info/METADATA
newmath-0.2.2.dist-info/WHEEL
newmath-0.2.2.dist-info/RECORD
