Metadata-Version: 2.1
Name: newmath
Version: 0.2.2
Summary: utilities for using NewBase60
License: BSD-2-Clause
Author: Angelo Gladding
Author-email: angelo@ragt.ag
Requires-Python: >=3.10,<3.11
Classifier: License :: OSI Approved :: BSD License
Classifier: Programming Language :: Python :: 3
Classifier: Programming Language :: Python :: 3.10
Requires-Dist: pycryptodome (>=3.16.0,<4.0.0)
